{
    "type": "minecraft:chest",
    "pools": [
        {
            "rolls": 1,
            "entries": [
                {
                    "type": "minecraft:item",
                    "name": "spectrum:purple_planks",
                    "functions": [
                        {
                            "function": "minecraft:set_count",
                            "count": {
                                "min": 4,
                                "max": 8
                            }
                        }
                    ]
                }
            ]
        },
        {
            "rolls": 1,
            "entries": [
                {
                    "type": "minecraft:item",
                    "name": "spectrum:mermaids_gem",
                    "functions": [
                        {
                            "function": "minecraft:set_count",
                            "count": {
                                "min": 4,
                                "max": 8
                            }
                        }
                    ]
                }
            ]
        },
        {
            "rolls": 1,
            "entries": [
                {
                    "type": "minecraft:item",
                    "name": "minecraft:honeycomb",
                    "functions": [
                        {
                            "function": "minecraft:set_count",
                            "count": {
                                "min": 2,
                                "max": 5
                            }
                        }
                    ]
                }
            ]
        },
        {
            "rolls": 1,
            "entries": [
                {
                    "type": "minecraft:item",
                    "name": "minecraft:sugar",
                    "functions": [
                        {
                            "function": "minecraft:set_count",
                            "count": {
                                "min": 4,
                                "max": 10
                            }
                        }
                    ]
                }
            ]
        },
        {
            "rolls": 1,
            "entries": [
                {
                    "type": "minecraft:item",
                    "name": "spectrum:nightdew_sprout",
                    "functions": [
                            {
                            "function": "minecraft:set_count",
                            "count": {
                                "min": 4,
                                "max": 8
                            }
                        }
                    ]
                }
            ]
        },
        {
            "rolls": 1,
            "entries": [
                {
                    "type": "minecraft:item",
                    "name": "spectrum:pure_coal",
                    "functions": [
                        {
                            "function": "minecraft:set_count",
                            "count": {
                                "min": 0,
                                "max": 4
                            }
                        }
                    ]
                }
            ]
        },
        {
            "rolls": 1,
            "entries": [
                {
                    "type": "minecraft:item",
                    "name": "minecraft:glass_bottle",
                    "functions": [
                        {
                            "function": "minecraft:set_count",
                            "count": {
                                "min": 4,
                                "max": 8
                            }
                        }
                    ]
                }
            ]
        },
        {
            "rolls": 1,
            "entries": [
                {
                    "type": "minecraft:item",
                    "name": "minecraft:potion",
                    "functions": [
                        {
                            "function": "minecraft:set_potion",
                            "id": "minecraft:water"
                        },
                        {
                            "function": "minecraft:set_count",
                            "count": {
                                "min": 0,
                                "max": 2
                            }
                        }
                    ]
                }
            ]
        },
        {
            "rolls": 1,
            "entries": [
                {
                    "type": "minecraft:item",
                    "name": "minecraft:air",
                    "weight": 1
                },
                {
                    "type": "minecraft:item",
                    "name": "spectrum:nectardew_burgeon",
                    "weight": 0,
                    "quality": 1.5
                }
            ]
        },
        {
            "rolls": 2,
            "entries": [
                {
                    "type": "minecraft:loot_table",
                    "name": "spectrum:chests/sub_tables/sleep_infused_beverages"
                }
            ],
            "conditions": [
                {
                    "condition": "minecraft:entity_properties",
                    "entity": "this",
                    "predicate": {
                        "type_specific": {
                            "type": "player",
                            "advancements": {
                                "spectrum:triggers/confirmed_drinking_age": true
                            }
                        }
                    }
                }
            ]
        }
    ]
}