{
  "name": "book.spectrum.guidebook.mod_integration.ae2.name",
  "icon": "ae2:controller",
  "condition": {
    "type": "modonomicon:and",
    "children": [
      {
        "type": "modonomicon:mod_loaded",
        "mod_id": "ae2"
      },
      {
        "type": "modonomicon:advancement",
        "advancement_id": "spectrum:place_pedestal"
      }
    ]
  },
  "category": "spectrum:mod_integration",
  "hide_while_locked": true,
  "parents": [],
  "background_u_index": 0,
  "background_v_index": 0,
  "x": 0,
  "y": 0,
  "pages": [
    {
      "type": "modonomicon:text",
      "text": "book.spectrum.guidebook.mod_integration.ae2.page0.text",
      "title": "book.spectrum.guidebook.mod_integration.ae2.name"
    },
    {
      "type": "modonomicon:spotlight",
      "title": "book.spectrum.guidebook.mod_integration.ae2.page1.title",
      "item": {
        "item": "ae2:growth_accelerator"
      },
      "text": "book.spectrum.guidebook.mod_integration.ae2.page1.text"
    },
    {
      "type": "modonomicon:spotlight",
      "title": "book.spectrum.guidebook.mod_integration.ae2.page2.title",
      "item": {
        "item": "ae2:quartz_cluster"
      },
      "condition": {
        "type": "modonomicon:advancement",
        "advancement_id": "spectrum:unlocks/blocks/crystal_apothecary"
      },
      "text": "book.spectrum.guidebook.mod_integration.ae2.page2.text"
    },
    {
      "type": "modonomicon:spotlight",
      "title": "book.spectrum.guidebook.mod_integration.ae2.page3.title",
      "condition": {
        "type": "modonomicon:advancement",
        "advancement_id": "spectrum:unlocks/enchantments/resonance_usage"
      },
      "item": {
        "item": "spectrum:resonant_pickaxe"
      },
      "text": "book.spectrum.guidebook.mod_integration.ae2.page3.text"
    },
    {
      "type": "spectrum:collection",
      "condition": {
        "type": "modonomicon:advancement",
        "advancement_id": "spectrum:unlocks/blocks/crystallarieum"
      },
      "title": "book.spectrum.guidebook.mod_integration.ae2.pure_resources.title",
      "items": [
        "spectrum:small_certus_quartz_bud",
        "spectrum:large_certus_quartz_bud",
        "spectrum:certus_quartz_cluster",
        "spectrum:pure_certus_quartz_block",
        "spectrum:pure_certus_quartz",
        "spectrum:small_fluix_bud",
        "spectrum:large_fluix_bud",
        "spectrum:fluix_cluster",
        "spectrum:pure_fluix_block",
        "spectrum:pure_fluix"
      ],
      "text": "book.spectrum.guidebook.mod_integration.ae2.pure_resources.text"
    },
    {
      "type": "spectrum:crystallarieum_growing",
      "title": "book.spectrum.guidebook.mod_integration.ae2.pure_certus_quartz_growing.title",
      "text": "book.spectrum.guidebook.mod_integration.ae2.pure_certus_quartz_growing.text",
      "recipe_id": "spectrum:mod_integration/ae2/crystallarieum/certus_quartz_crystal"
    },
    {
      "type": "spectrum:crystallarieum_growing",
      "title": "book.spectrum.guidebook.mod_integration.ae2.pure_fluix_crystal_growing.title",
      "text": "book.spectrum.guidebook.mod_integration.ae2.pure_fluix_crystal_growing.text",
      "recipe_id": "spectrum:mod_integration/ae2/crystallarieum/fluix_crystal"
    },
    {
      "type": "spectrum:anvil_crushing",
      "title": "container.spectrum.rei.anvil_crushing.title",
      "recipe_id": "spectrum:mod_integration/ae2/anvil_crushing/certus_quartz_dust",
      "text": "book.spectrum.guidebook.mod_integration.ae2.page4.text"
    },
    {
      "type": "spectrum:fusion_shrine_crafting",
      "text": "book.spectrum.guidebook.mod_integration.ae2.page5.text",
      "recipe_id": "spectrum:mod_integration/ae2/fusion_shrine/charged_certus_quartz_crystal"
    },
    {
      "type": "spectrum:fusion_shrine_crafting",
      "text": "book.spectrum.guidebook.mod_integration.ae2.page6.text",
      "title": "container.spectrum.rei.anvil_crushing.title",
      "recipe_id": "spectrum:mod_integration/ae2/fusion_shrine/fluix_crystal"
    },
    {
      "type": "spectrum:cinderhearth_smelting",
      "title": "book.spectrum.guidebook.mod_integration.ae2.silicon_from_rock_crystal.title",
      "text": "book.spectrum.guidebook.mod_integration.ae2.silicon_from_rock_crystal.text",
      "recipe_id": "spectrum:mod_integration/ae2/cinderhearth/silicon_from_rock_crystal"
    }
  ]
}
