{
  "name": "book.spectrum.guidebook.spawner_manipulation.name",
  "condition": {
    "type": "modonomicon:advancement",
    "advancement_id": "spectrum:milestones/unlock_spawner_manipulation"
  },
  "icon": "minecraft:spawner",
  "category": "spectrum:creating_life",
  "hide_while_locked": true,
  "parents": [
    {
      "entry": "spectrum:creating_life/mob_heads"
    },
    {
      "entry": "spectrum:creating_life/spirit_instiller"
    }
  ],
  "background_u_index": 0,
  "background_v_index": 1,
  "x": -1,
  "y": 3,
  "pages": [
    {
      "type": "modonomicon:spotlight",
      "title": "book.spectrum.guidebook.harvesting_spawners",
      "item": {
        "item": "spectrum:resonant_pickaxe"
      },
			"text": "book.spectrum.guidebook.spawner_manipulation.intro.text"
    },
    {
      "type": "spectrum:spirit_instiller_crafting",
			"title": "book.spectrum.guidebook.spawner_manipulation.spawn_count_change.title",
      "recipe_id": "spectrum:spirit_instiller/spawner/spawner_spawn_count_change",
			"text": "book.spectrum.guidebook.spawner_manipulation.spawn_count_change.text"
    },
    {
      "type": "spectrum:spirit_instiller_crafting",
			"title": "book.spectrum.guidebook.spawner_manipulation.spawn_delay_change.title",
      "recipe_id": "spectrum:spirit_instiller/spawner/spawner_spawn_delay_change",
			"text": "book.spectrum.guidebook.spawner_manipulation.spawn_delay_change.text"
    },
    {
      "type": "spectrum:spirit_instiller_crafting",
			"title": "book.spectrum.guidebook.spawner_manipulation.max_nearby_entities_change.title",
      "recipe_id": "spectrum:spirit_instiller/spawner/spawner_max_nearby_entities_change",
			"text": "book.spectrum.guidebook.spawner_manipulation.max_nearby_entities_change.text"
    },
    {
      "type": "spectrum:spirit_instiller_crafting",
			"title": "book.spectrum.guidebook.spawner_manipulation.required_player_range_change.title",
      "recipe_id": "spectrum:spirit_instiller/spawner/spawner_required_player_range_change",
			"text": "book.spectrum.guidebook.spawner_manipulation.required_player_range_change.text"
    }
  ]
}
